[{"model": "brapi.obstrait", "pk": 1, "fields": {"traitDbId": "CO_334:0100630", "name": "Canopy temperature", "classe": "", "description": "", "synonyms": "", "mainAbbreviation": "", "alternativeAbbreviations": "", "entity": "", "attribute": "", "status": "", "xref": "", "uniqueDisplayName": "", "extractDbId": null, "markerprofileDbId": null, "analysisMethod": "", "data": ""}}, {"model": "brapi.obstrait", "pk": 2, "fields": {"traitDbId": "CO_334:0100620", "name": "Carotenoid content", "classe": "physiological trait", "description": "Cassava storage root pulp carotenoid content", "synonyms": "carotenoid content measure", "mainAbbreviation": "CC", "alternativeAbbreviations": "CCS", "entity": "root", "attribute": "carotenoid", "status": "recommended", "xref": "TL_455:0003023", "uniqueDisplayName": "", "extractDbId": null, "markerprofileDbId": null, "analysisMethod": "", "data": ""}}]